neuronexpert/__init__.py
neuronexpert/neuronexpert.py
neuronexpert-1.0.2.dist-info/METADATA
neuronexpert-1.0.2.dist-info/WHEEL
neuronexpert-1.0.2.dist-info/top_level.txt
neuronexpert-1.0.2.dist-info/RECORD
