Metadata-Version: 2.1
Name: neuronexpert
Version: 1.0.2
Summary: This is the lib to use Neuron Expert Assistant
Home-page: https://neuron.expert
Author: percyve11e
Author-email: percyve11e.me@gmail.com
Project-URL: GitHub, https://github.com/nnevdokimov
Keywords: neuron expert
Classifier: Programming Language :: Python :: 3.11
Classifier: License :: OSI Approved :: MIT License
Classifier: Operating System :: OS Independent
Requires-Python: >=3.6
Requires-Dist: requests >=2.25.1
Requires-Dist: aiohttp
